pydoubao/__init__.py
pydoubao/pydoubao.py
pydoubao-0.1.6.dist-info/LICENSE
pydoubao-0.1.6.dist-info/METADATA
pydoubao-0.1.6.dist-info/WHEEL
pydoubao-0.1.6.dist-info/top_level.txt
pydoubao-0.1.6.dist-info/RECORD
