Metadata-Version: 2.1
Name: pydoubao
Version: 0.1.6
Summary: Use doubao web api to build a chatbot, without using doubao API which need token fee.
Home-page: https://pypi.org/project/pydoubao/
Author: Wenhao Liu
Author-email: me@liuwenhao.me
License: UNKNOWN
Platform: UNKNOWN
Classifier: Programming Language :: Python :: 3
Classifier: License :: OSI Approved :: MIT License
Classifier: Operating System :: OS Independent
Requires-Python: >=3.6
Requires-Dist: requests
